causalenv/__init__.py
causalenv/envs/__init__.py
causalenv/envs/causal_env.py
causalenv-0.1.3.dist-info/WHEEL
causalenv-0.1.3.dist-info/METADATA
causalenv-0.1.3.dist-info/RECORD
