Metadata-Version: 2.1
Name: causalenv
Version: 0.1.3
Summary: 
Author: Elias Aoun Durand
Author-email: elias.aoundurand@gmail.com
Requires-Python: >=3.8,<4.0
Classifier: Programming Language :: Python :: 3
Classifier: Programming Language :: Python :: 3.8
Classifier: Programming Language :: Python :: 3.9
Requires-Dist: gym (>=0.18.0,<0.19.0)
Requires-Dist: setuptools (>=57.0,<58.0)
